src/__init__.py
src/main.py
pnoj_tg-20.6.0.dist-info/LICENSE
pnoj_tg-20.6.0.dist-info/METADATA
pnoj_tg-20.6.0.dist-info/WHEEL
pnoj_tg-20.6.0.dist-info/entry_points.txt
pnoj_tg-20.6.0.dist-info/top_level.txt
pnoj_tg-20.6.0.dist-info/RECORD
