Metadata-Version: 2.1
Name: pnoj-tg
Version: 20.6.0
Summary: A testcase generator for the PNOJ Online Judge.
Home-page: https://github.com/pnoj/pnoj-tg
Author: PNOJ Authors
Author-email: contact@paullee.dev
License: UNKNOWN
Platform: UNKNOWN
Classifier: Development Status :: 5 - Production/Stable
Classifier: Programming Language :: Python :: 3
Classifier: License :: OSI Approved :: MIT License
Classifier: Operating System :: OS Independent
Classifier: Topic :: Software Development :: Code Generators
Requires-Python: >=3.6
Requires-Dist: pyyaml
